mcp_server_code_assist/__init__.py
mcp_server_code_assist/__main__.py
mcp_server_code_assist/schema.xsd
mcp_server_code_assist/server.py
mcp_server_code_assist/xml_parser.py
mcp_server_code_assist/tools/__init__.py
mcp_server_code_assist/tools/file_tools.py
mcp_server_code_assist/tools/git_functions.py
mcp_server_code_assist/tools/invoke.py
mcp_server_code_assist/tools/models.py
mcp_server_code_assist/tools/repository_tools.py
mcp_server_code_assist-0.1.3.dist-info/METADATA
mcp_server_code_assist-0.1.3.dist-info/WHEEL
mcp_server_code_assist-0.1.3.dist-info/entry_points.txt
mcp_server_code_assist-0.1.3.dist-info/RECORD
